{
  "materials": [
    {
      "Kd": [1, 0, 0],
      "Ke": [0, 0, 0]
    },
    {
      "Kd": [0.7, 0.5, 0.5],
      "Ke": [0.7, 0.5, 0.5]
    }
  ],
  "triangles": [
    {
      "name": "floor1",
      "p1": [5.1, -5, -5],
      "p2": [-5.1, -5, -5],
      "p3": [5.1, -5, 0],
      "matId": 0
    },
    {
      "name": "floor2",
      "p1": [-5.1, -5, 0],
      "p2": [5.1, -5, 0],
      "p3": [-5.1, -5, -5],
      "matId": 0
    },
    {
      "name": "light",
      "p1": [-2.5, 5, -3.5],
      "p2": [2.5, 5, -1.5],
      "p3": [2.5, 5, -3.5],
      "matId": 1
    }
  ],
  "models": [
    {
      "objFile": "../assets/deer.obj",
      "mtlBasedir": "",
      "scale": 1,
      "translation": [0, 0, 0]
    }
  ]

}